pre_workbench/.__main__.py.swp
pre_workbench/LICENSE
pre_workbench/__init__.py
pre_workbench/__main__.py
pre_workbench/_version.py
pre_workbench/app.py
pre_workbench/bbuf_parsing.py
pre_workbench/configs.py
pre_workbench/consts.py
pre_workbench/datasource.py
pre_workbench/datawidgets.py
pre_workbench/errorhandler.py
pre_workbench/format_info.tes
pre_workbench/guihelper.py
pre_workbench/interactive_fic.py
pre_workbench/mainwindow.py
pre_workbench/meta_schema.tes
pre_workbench/objects.py
pre_workbench/project.py
pre_workbench/rangetree.py
pre_workbench/settingsgroup.tes
pre_workbench/stylesheet.css
pre_workbench/syshelper.py
pre_workbench/syshelper_linux.py
pre_workbench/syshelper_macos.py
pre_workbench/syshelper_win.py
pre_workbench/tshark_helper.py
pre_workbench/typeeditor.py
pre_workbench/typeregistry.py
pre_workbench/util.py
pre_workbench/wrapper.py
pre_workbench/algo/__init__.py
pre_workbench/algo/range.c
pre_workbench/algo/range.cpython-39-darwin.so
pre_workbench/algo/range.pyx
pre_workbench/algo/rangelist.c
pre_workbench/algo/rangelist.cpython-39-darwin.so
pre_workbench/algo/rangelist.pyx
pre_workbench/controls/__init__.py
pre_workbench/controls/genericwidgets.py
pre_workbench/controls/hexview.py
pre_workbench/controls/hexview_selheur.py
pre_workbench/controls/scintillaedit.py
pre_workbench/cpp/qtcolorpicker/configure.py
pre_workbench/cpp/qtcolorpicker/pyproject.toml
pre_workbench/cpp/qtcolorpicker/qtcolorpicker.cpp
pre_workbench/cpp/qtcolorpicker/qtcolorpicker.h
pre_workbench/cpp/qtcolorpicker/qtcolorpicker.sip
pre_workbench/cpp/qtcolorpicker/test.py
pre_workbench/icons/appicon.png
pre_workbench/icons/application--plus.png
pre_workbench/icons/applications-stack.png
pre_workbench/icons/arrow-circle-double.png
pre_workbench/icons/beaker.png
pre_workbench/icons/binocular-flag.png
pre_workbench/icons/blue-folder-horizontal-open.png
pre_workbench/icons/bookmarks.png
pre_workbench/icons/box.png
pre_workbench/icons/bug--exclamation.png
pre_workbench/icons/bug.png
pre_workbench-0.9.0.dist-info/LICENSE
pre_workbench-0.9.0.dist-info/METADATA
pre_workbench-0.9.0.dist-info/WHEEL
pre_workbench-0.9.0.dist-info/entry_points.txt
pre_workbench-0.9.0.dist-info/top_level.txt
pre_workbench-0.9.0.dist-info/RECORD
