Metadata-Version: 2.1
Name: pre-workbench
Version: 0.9.0
Summary: Protocol Reverse Engineering Workbench
Home-page: https://github.com/pre-workbench
Author: Mira Weller
Author-email: mweller@seemoo.tu-darmstadt.de
Classifier: Programming Language :: Python :: 3
Classifier: License :: OSI Approved :: GNU General Public License v3 or later (GPLv3+)
Classifier: Topic :: System :: Networking
Classifier: Environment :: X11 Applications :: Qt
Classifier: Operating System :: OS Independent
License-File: LICENSE
Requires-Dist: PyQt5 (>=5.11.3)
Requires-Dist: appdirs (>=1.4.3)
Requires-Dist: QScintilla (>=2.11.2)
Requires-Dist: lark-parser (>=0.7.5)
Requires-Dist: psutil (>=5.0.0)
Requires-Dist: bitstring (>=3.1.9)
Requires-Dist: PyQtAds (>=3.8.1)
Requires-Dist: darkdetect (==0.6.0)
Requires-Dist: PyYAML (>=6.0)
